{
  "project_info": {
    "project_number": "828309903998",
    "firebase_url": "https://amst-g5-lab5-flutter-default-rtdb.firebaseio.com",
    "project_id": "amst-g5-lab5-flutter",
    "storage_bucket": "amst-g5-lab5-flutter.appspot.com"
  },
  "client": [
    {
      "client_info": {
        "mobilesdk_app_id": "1:828309903998:android:f4a64dbae483436c60562f",
        "android_client_info": {
          "package_name": "com.example.amst5_g1"
        }
      },
      "oauth_client": [
        {
          "client_id": "828309903998-2qnffq86jbmjg9s6g90m0e8psh1kbib0.apps.googleusercontent.com",
          "client_type": 3
        }
      ],
      "api_key": [
        {
          "current_key": "AIzaSyAo0Ay0-wTZ70olWT0NwsUTjUYeRkEOJrw"
        }
      ],
      "services": {
        "appinvite_service": {
          "other_platform_oauth_client": [
            {
              "client_id": "828309903998-2qnffq86jbmjg9s6g90m0e8psh1kbib0.apps.googleusercontent.com",
              "client_type": 3
            },
            {
              "client_id": "828309903998-55ucttiatrd1ltq1nm2qu38o0onma7do.apps.googleusercontent.com",
              "client_type": 2,
              "ios_info": {
                "bundle_id": "com.example.amstG5Lab5"
              }
            }
          ]
        }
      }
    },
    {
      "client_info": {
        "mobilesdk_app_id": "1:828309903998:android:d10b11b94225da6460562f",
        "android_client_info": {
          "package_name": "com.example.amst_g5_lab5"
        }
      },
      "oauth_client": [
        {
          "client_id": "828309903998-2qnffq86jbmjg9s6g90m0e8psh1kbib0.apps.googleusercontent.com",
          "client_type": 3
        }
      ],
      "api_key": [
        {
          "current_key": "AIzaSyAo0Ay0-wTZ70olWT0NwsUTjUYeRkEOJrw"
        }
      ],
      "services": {
        "appinvite_service": {
          "other_platform_oauth_client": [
            {
              "client_id": "828309903998-2qnffq86jbmjg9s6g90m0e8psh1kbib0.apps.googleusercontent.com",
              "client_type": 3
            },
            {
              "client_id": "828309903998-55ucttiatrd1ltq1nm2qu38o0onma7do.apps.googleusercontent.com",
              "client_type": 2,
              "ios_info": {
                "bundle_id": "com.example.amstG5Lab5"
              }
            }
          ]
        }
      }
    }
  ],
  "configuration_version": "1"
}